mofchecker/__init__.py
mofchecker/cli.py
mofchecker/definitions.py
mofchecker/errors.py
mofchecker/types.py
mofchecker/utils.py
mofchecker/version.py
mofchecker/checks/__init__.py
mofchecker/checks/charge_check.py
mofchecker/checks/check_base.py
mofchecker/checks/floating_solvent.py
mofchecker/checks/zeopp.py
mofchecker/checks/data/__init__.py
mofchecker/checks/data/definitions.py
mofchecker/checks/global_structure/__init__.py
mofchecker/checks/global_structure/graphcheck.py
mofchecker/checks/local_structure/__init__.py
mofchecker/checks/local_structure/base_coordination_check.py
mofchecker/checks/local_structure/base_missing_check.py
mofchecker/checks/local_structure/false_oxo.py
mofchecker/checks/local_structure/geometrically_exposed_metal.py
mofchecker/checks/local_structure/geometry.py
mofchecker/checks/local_structure/overcoordinated_carbon.py
mofchecker/checks/local_structure/overcoordinated_hydrogen.py
mofchecker/checks/local_structure/overcoordinated_nitrogen.py
mofchecker/checks/local_structure/overlapping_atoms.py
mofchecker/checks/local_structure/undercoordinated_alkaline.py
mofchecker/checks/local_structure/undercoordinated_carbon.py
mofchecker/checks/local_structure/undercoordinated_nitrogen.py
mofchecker/checks/local_structure/undercoordinated_rare_earth.py
mofchecker/checks/oms/__init__.py
mofchecker/checks/oms/definitions.py
mofchecker/checks/oms/errors.py
mofchecker/checks/utils/__init__.py
mofchecker/checks/utils/geometry.py
mofchecker/checks/utils/get_indices.py
mofchecker/database/__init__.py
mofchecker/database/composition_dict.pkl
mofchecker/database/graph_hash_dict.pkl
mofchecker/database/scaffold_hash_dict.pkl
mofchecker/database/symmetry_hash_dict.pkl
mofchecker/symmetry/__init__.py
mofchecker/symmetry/hash.py
mofchecker-0.9.6.dist-info/LICENSE
mofchecker-0.9.6.dist-info/METADATA
mofchecker-0.9.6.dist-info/WHEEL
mofchecker-0.9.6.dist-info/entry_points.txt
mofchecker-0.9.6.dist-info/top_level.txt
mofchecker-0.9.6.dist-info/RECORD
