Metadata-Version: 2.1
Name: mofchecker
Version: 0.9.6
Summary: Perform sanity checks for MOFs.
Home-page: https://github.com/kjappelbaum/mofchecker
Download-URL: https://github.com/kjappelbaum/mofchecker/releases
Author: Kevin Jablonka
Author-email: mail@kjablonka.com
Maintainer: Kevin Jablonka
Maintainer-email: mail@kjablonka.com
License: MIT
Project-URL: Bug Tracker, https://github.com/kjappelbaum/mofchecker/issues
Project-URL: Source Code, https://github.com/kjappelbaum/mofchecker
Classifier: Development Status :: 1 - Planning
Classifier: Environment :: Console
Classifier: Intended Audience :: Developers
Classifier: License :: OSI Approved :: MIT License
Classifier: Operating System :: OS Independent
Classifier: Framework :: Pytest
Classifier: Framework :: tox
Classifier: Framework :: Sphinx
Classifier: Programming Language :: Python
Classifier: Programming Language :: Python :: 3.8
Classifier: Programming Language :: Python :: 3.9
Classifier: Programming Language :: Python :: 3.10
Classifier: Programming Language :: Python :: 3 :: Only
Requires-Python: >=3.8
License-File: LICENSE
Requires-Dist: click
Requires-Dist: networkx (>=2.5)
Requires-Dist: backports.cached-property
Requires-Dist: ase
Requires-Dist: pyyaml
Requires-Dist: pyeqeq
Requires-Dist: structuregraph-helpers
Requires-Dist: element-coder
Requires-Dist: typing-extensions
Requires-Dist: libconeangle
Provides-Extra: docs
Requires-Dist: sphinx ; extra == 'docs'
Requires-Dist: furo ; extra == 'docs'
Requires-Dist: sphinx-click ; extra == 'docs'
Requires-Dist: sphinx-autodoc-typehints ; extra == 'docs'
Requires-Dist: sphinx-automodapi ; extra == 'docs'
Requires-Dist: sphinx-copybutton ; extra == 'docs'
Provides-Extra: lint
Requires-Dist: isort ; extra == 'lint'
Requires-Dist: black ; extra == 'lint'
Requires-Dist: flake8 ; extra == 'lint'
Requires-Dist: pre-commit ; extra == 'lint'
Requires-Dist: bumpversion ; extra == 'lint'
Provides-Extra: tests
Requires-Dist: pytest ; extra == 'tests'
Requires-Dist: tox ; extra == 'tests'
Requires-Dist: coverage ; extra == 'tests'
